simweights/__init__.py
simweights/_corsika_weighter.py
simweights/_fluxes.py
simweights/_generation_surface.py
simweights/_genie_weighter.py
simweights/_icetop_weighter.py
simweights/_nugen_weighter.py
simweights/_pdgcode.py
simweights/_powerlaw.py
simweights/_spatial.py
simweights/_utils.py
simweights/_weighter.py
simweights/cmdline.py
simweights/gsf_data_table.txt
simweights-0.1.3.dist-info/entry_points.txt
simweights-0.1.3.dist-info/COPYING
simweights-0.1.3.dist-info/WHEEL
simweights-0.1.3.dist-info/METADATA
simweights-0.1.3.dist-info/RECORD
