Metadata-Version: 2.3
Name: simweights
Version: 0.1.3
Summary: Pure python library for calculating the weights of Monte Carlo simulation for IceCube.
Keywords: python,science,astronomy,astrophysics,IceCube,neutrino,simulation
Author: Kevin Meagher
Requires-Python: ~=3.8
Classifier: Development Status :: 4 - Beta
Classifier: Intended Audience :: Science/Research
Classifier: License :: OSI Approved :: BSD License
Classifier: Operating System :: MacOS :: MacOS X
Classifier: Operating System :: POSIX :: Linux
Classifier: Programming Language :: Python
Classifier: Programming Language :: Python :: 3.8
Classifier: Programming Language :: Python :: 3.9
Classifier: Programming Language :: Python :: 3.10
Classifier: Programming Language :: Python :: 3.11
Classifier: Programming Language :: Python :: 3.12
Classifier: Programming Language :: Python :: 3.13
Classifier: Topic :: Scientific/Engineering :: Astronomy
Classifier: Topic :: Scientific/Engineering :: Physics
Requires-Dist: numpy>=1.21.2
Requires-Dist: scipy
Requires-Dist: pytest ; extra == "dev"
Requires-Dist: pre-commit ; extra == "dev"
Requires-Dist: reuse ; extra == "dev"
Requires-Dist: black ; extra == "dev"
Requires-Dist: ruff ; extra == "dev"
Requires-Dist: pylint ; extra == "dev"
Requires-Dist: mypy ; extra == "dev"
Requires-Dist: sphinx ; extra == "docs"
Requires-Dist: sphinx-rtd-theme ; extra == "docs"
Requires-Dist: pandas ; extra == "docs"
Requires-Dist: matplotlib ; extra == "examples"
Requires-Dist: h5py ; extra == "test"
Requires-Dist: tables ; extra == "test"
Requires-Dist: pandas ; extra == "test"
Requires-Dist: uproot ; extra == "test"
Requires-Dist: pytest-cov ; extra == "test"
Requires-Dist: pytest-regressions ; extra == "test"
Project-URL: Collaboration, https://icecube.wisc.edu
Project-URL: Documentation, https://docs.icecube.aq/simweights/main
Project-URL: Source, https://github.com/icecube/simweights
Provides-Extra: dev
Provides-Extra: docs
Provides-Extra: examples
Provides-Extra: test
